{"version":1,"sourceHash":0,"idRange":[],"name":"ChatterGroups","typeName":"ConnectApi.ChatterGroups","nature":"class","modifiers":["public","virtual"],"superClass":"","interfaces":[],"fields":[],"constructors":[{"version":1,"modifiers":["public"],"parameters":[],"dependents":[]}],"methods":[{"version":1,"name":"addMember","modifiers":["public","static"],"typeName":"ConnectApi.GroupMember","parameters":[{"version":1,"name":"communityId","typeName":"System.String"},{"version":1,"name":"groupId","typeName":"System.String"},{"version":1,"name":"userId","typeName":"System.String"}],"dependents":[]},{"version":1,"name":"addMemberWithRole","modifiers":["public","static"],"typeName":"ConnectApi.GroupMember","parameters":[{"version":1,"name":"communityId","typeName":"System.String"},{"version":1,"name":"groupId","typeName":"System.String"},{"version":1,"name":"userId","typeName":"System.String"},{"version":1,"name":"role","typeName":"ConnectApi.GroupMembershipType"}],"dependents":[]},{"version":1,"name":"addRecord","modifiers":["public","static"],"typeName":"ConnectApi.GroupRecord","parameters":[{"version":1,"name":"communityId","typeName":"System.String"},{"version":1,"name":"groupId","typeName":"System.String"},{"version":1,"name":"recordId","typeName":"System.String"}],"dependents":[]},{"version":1,"name":"createGroup","modifiers":["public","static"],"typeName":"ConnectApi.ChatterGroupDetail","parameters":[{"version":1,"name":"communityId","typeName":"System.String"},{"version":1,"name":"groupInput","typeName":"ConnectApi.ChatterGroupInput"}],"dependents":[]},{"version":1,"name":"deleteBannerPhoto","modifiers":["public","static"],"typeName":"void","parameters":[{"version":1,"name":"communityId","typeName":"System.String"},{"version":1,"name":"groupId","typeName":"System.String"}],"dependents":[]},{"version":1,"name":"deleteGroup","modifiers":["public","static"],"typeName":"void","parameters":[{"version":1,"name":"communityId","typeName":"System.String"},{"version":1,"name":"groupId","typeName":"System.String"}],"dependents":[]},{"version":1,"name":"deleteMember","modifiers":["public","static"],"typeName":"void","parameters":[{"version":1,"name":"communityId","typeName":"System.String"},{"version":1,"name":"membershipId","typeName":"System.String"}],"dependents":[]},{"version":1,"name":"deletePhoto","modifiers":["public","static"],"typeName":"void","parameters":[{"version":1,"name":"communityId","typeName":"System.String"},{"version":1,"name":"groupId","typeName":"System.String"}],"dependents":[]},{"version":1,"name":"follow","modifiers":["public","static"],"typeName":"ConnectApi.Subscription","parameters":[{"version":1,"name":"communityId","typeName":"System.String"},{"version":1,"name":"groupId","typeName":"System.String"},{"version":1,"name":"subjectId","typeName":"System.String"}],"dependents":[]},{"version":1,"name":"getAnnouncements","modifiers":["public","static"],"typeName":"ConnectApi.AnnouncementPage","parameters":[{"version":1,"name":"communityId","typeName":"System.String"},{"version":1,"name":"groupId","typeName":"System.String"},{"version":1,"name":"pageParam","typeName":"System.Integer"},{"version":1,"name":"pageSize","typeName":"System.Integer"}],"dependents":[]},{"version":1,"name":"getAnnouncements","modifiers":["public","static"],"typeName":"ConnectApi.AnnouncementPage","parameters":[{"version":1,"name":"communityId","typeName":"System.String"},{"version":1,"name":"groupId","typeName":"System.String"}],"dependents":[]},{"version":1,"name":"getBannerPhoto","modifiers":["public","static"],"typeName":"ConnectApi.BannerPhoto","parameters":[{"version":1,"name":"communityId","typeName":"System.String"},{"version":1,"name":"groupId","typeName":"System.String"}],"dependents":[]},{"version":1,"name":"getFollowings","modifiers":["public","static"],"typeName":"ConnectApi.FollowingPage","parameters":[{"version":1,"name":"communityId","typeName":"System.String"},{"version":1,"name":"groupId","typeName":"System.String"},{"version":1,"name":"filterType","typeName":"System.String"},{"version":1,"name":"pageParam","typeName":"System.Integer"},{"version":1,"name":"pageSize","typeName":"System.Integer"}],"dependents":[]},{"version":1,"name":"getFollowings","modifiers":["public","static"],"typeName":"ConnectApi.FollowingPage","parameters":[{"version":1,"name":"communityId","typeName":"System.String"},{"version":1,"name":"groupId","typeName":"System.String"}],"dependents":[]},{"version":1,"name":"getFollowings","modifiers":["public","static"],"typeName":"ConnectApi.FollowingPage","parameters":[{"version":1,"name":"communityId","typeName":"System.String"},{"version":1,"name":"groupId","typeName":"System.String"},{"version":1,"name":"pageParam","typeName":"System.Integer"}],"dependents":[]},{"version":1,"name":"getFollowings","modifiers":["public","static"],"typeName":"ConnectApi.FollowingPage","parameters":[{"version":1,"name":"communityId","typeName":"System.String"},{"version":1,"name":"groupId","typeName":"System.String"},{"version":1,"name":"pageParam","typeName":"System.Integer"},{"version":1,"name":"pageSize","typeName":"System.Integer"}],"dependents":[]},{"version":1,"name":"getFollowings","modifiers":["public","static"],"typeName":"ConnectApi.FollowingPage","parameters":[{"version":1,"name":"communityId","typeName":"System.String"},{"version":1,"name":"groupId","typeName":"System.String"},{"version":1,"name":"filterType","typeName":"System.String"}],"dependents":[]},{"version":1,"name":"getFollowings","modifiers":["public","static"],"typeName":"ConnectApi.FollowingPage","parameters":[{"version":1,"name":"communityId","typeName":"System.String"},{"version":1,"name":"groupId","typeName":"System.String"},{"version":1,"name":"filterType","typeName":"System.String"},{"version":1,"name":"pageParam","typeName":"System.Integer"}],"dependents":[]},{"version":1,"name":"getGroup","modifiers":["public","static"],"typeName":"ConnectApi.ChatterGroupDetail","parameters":[{"version":1,"name":"communityId","typeName":"System.String"},{"version":1,"name":"groupId","typeName":"System.String"}],"dependents":[]},{"version":1,"name":"getGroupBatch","modifiers":["public","static"],"typeName":"System.List<ConnectApi.BatchResult>","parameters":[{"version":1,"name":"communityId","typeName":"System.String"},{"version":1,"name":"groupIds","typeName":"System.List<System.String>"}],"dependents":[]},{"version":1,"name":"getGroupMembershipRequest","modifiers":["public","static"],"typeName":"ConnectApi.GroupMembershipRequest","parameters":[{"version":1,"name":"communityId","typeName":"System.String"},{"version":1,"name":"requestId","typeName":"System.String"}],"dependents":[]},{"version":1,"name":"getGroupMembershipRequests","modifiers":["public","static"],"typeName":"ConnectApi.GroupMembershipRequests","parameters":[{"version":1,"name":"communityId","typeName":"System.String"},{"version":1,"name":"groupId","typeName":"System.String"}],"dependents":[]},{"version":1,"name":"getGroupMembershipRequests","modifiers":["public","static"],"typeName":"ConnectApi.GroupMembershipRequests","parameters":[{"version":1,"name":"communityId","typeName":"System.String"},{"version":1,"name":"groupId","typeName":"System.String"},{"version":1,"name":"status","typeName":"ConnectApi.GroupMembershipRequestStatus"}],"dependents":[]},{"version":1,"name":"getGroups","modifiers":["public","static"],"typeName":"ConnectApi.ChatterGroupPage","parameters":[{"version":1,"name":"communityId","typeName":"System.String"},{"version":1,"name":"pageParam","typeName":"System.Integer"},{"version":1,"name":"pageSize","typeName":"System.Integer"}],"dependents":[]},{"version":1,"name":"getGroups","modifiers":["public","static"],"typeName":"ConnectApi.ChatterGroupPage","parameters":[{"version":1,"name":"communityId","typeName":"System.String"},{"version":1,"name":"archiveStatus","typeName":"ConnectApi.GroupArchiveStatus"},{"version":1,"name":"pageParam","typeName":"System.Integer"},{"version":1,"name":"pageSize","typeName":"System.Integer"}],"dependents":[]},{"version":1,"name":"getGroups","modifiers":["public","static"],"typeName":"ConnectApi.ChatterGroupPage","parameters":[{"version":1,"name":"communityId","typeName":"System.String"}],"dependents":[]},{"version":1,"name":"getMember","modifiers":["public","static"],"typeName":"ConnectApi.GroupMember","parameters":[{"version":1,"name":"communityId","typeName":"System.String"},{"version":1,"name":"membershipId","typeName":"System.String"}],"dependents":[]},{"version":1,"name":"getMembers","modifiers":["public","static"],"typeName":"ConnectApi.GroupMemberPage","parameters":[{"version":1,"name":"communityId","typeName":"System.String"},{"version":1,"name":"groupId","typeName":"System.String"},{"version":1,"name":"pageParam","typeName":"System.Integer"},{"version":1,"name":"pageSize","typeName":"System.Integer"}],"dependents":[]},{"version":1,"name":"getMembers","modifiers":["public","static"],"typeName":"ConnectApi.GroupMemberPage","parameters":[{"version":1,"name":"communityId","typeName":"System.String"},{"version":1,"name":"groupId","typeName":"System.String"}],"dependents":[]},{"version":1,"name":"getMembershipBatch","modifiers":["public","static"],"typeName":"System.List<ConnectApi.BatchResult>","parameters":[{"version":1,"name":"communityId","typeName":"System.String"},{"version":1,"name":"membershipIds","typeName":"System.List<System.String>"}],"dependents":[]},{"version":1,"name":"getMyChatterSettings","modifiers":["public","static"],"typeName":"ConnectApi.GroupChatterSettings","parameters":[{"version":1,"name":"communityId","typeName":"System.String"},{"version":1,"name":"groupId","typeName":"System.String"}],"dependents":[]},{"version":1,"name":"getPhoto","modifiers":["public","static"],"typeName":"ConnectApi.Photo","parameters":[{"version":1,"name":"communityId","typeName":"System.String"},{"version":1,"name":"groupId","typeName":"System.String"}],"dependents":[]},{"version":1,"name":"getRecord","modifiers":["public","static"],"typeName":"ConnectApi.GroupRecord","parameters":[{"version":1,"name":"communityId","typeName":"System.String"},{"version":1,"name":"groupRecordId","typeName":"System.String"}],"dependents":[]},{"version":1,"name":"getRecords","modifiers":["public","static"],"typeName":"ConnectApi.GroupRecordPage","parameters":[{"version":1,"name":"communityId","typeName":"System.String"},{"version":1,"name":"groupId","typeName":"System.String"},{"version":1,"name":"pageParam","typeName":"System.Integer"},{"version":1,"name":"pageSize","typeName":"System.Integer"}],"dependents":[]},{"version":1,"name":"getRecords","modifiers":["public","static"],"typeName":"ConnectApi.GroupRecordPage","parameters":[{"version":1,"name":"communityId","typeName":"System.String"},{"version":1,"name":"groupId","typeName":"System.String"}],"dependents":[]},{"version":1,"name":"inviteUsers","modifiers":["public","static"],"typeName":"ConnectApi.Invitations","parameters":[{"version":1,"name":"groupId","typeName":"System.String"},{"version":1,"name":"invite","typeName":"ConnectApi.InviteInput"}],"dependents":[]},{"version":1,"name":"postAnnouncement","modifiers":["public","static"],"typeName":"ConnectApi.Announcement","parameters":[{"version":1,"name":"communityId","typeName":"System.String"},{"version":1,"name":"groupId","typeName":"System.String"},{"version":1,"name":"announcement","typeName":"ConnectApi.AnnouncementInput"}],"dependents":[]},{"version":1,"name":"removeRecord","modifiers":["public","static"],"typeName":"void","parameters":[{"version":1,"name":"communityId","typeName":"System.String"},{"version":1,"name":"groupRecordId","typeName":"System.String"}],"dependents":[]},{"version":1,"name":"requestGroupMembership","modifiers":["public","static"],"typeName":"ConnectApi.GroupMembershipRequest","parameters":[{"version":1,"name":"communityId","typeName":"System.String"},{"version":1,"name":"groupId","typeName":"System.String"}],"dependents":[]},{"version":1,"name":"searchGroups","modifiers":["public","static"],"typeName":"ConnectApi.ChatterGroupPage","parameters":[{"version":1,"name":"communityId","typeName":"System.String"},{"version":1,"name":"q","typeName":"System.String"},{"version":1,"name":"archiveStatus","typeName":"ConnectApi.GroupArchiveStatus"},{"version":1,"name":"pageParam","typeName":"System.Integer"},{"version":1,"name":"pageSize","typeName":"System.Integer"}],"dependents":[]},{"version":1,"name":"searchGroups","modifiers":["public","static"],"typeName":"ConnectApi.ChatterGroupPage","parameters":[{"version":1,"name":"communityId","typeName":"System.String"},{"version":1,"name":"q","typeName":"System.String"}],"dependents":[]},{"version":1,"name":"searchGroups","modifiers":["public","static"],"typeName":"ConnectApi.ChatterGroupPage","parameters":[{"version":1,"name":"communityId","typeName":"System.String"},{"version":1,"name":"q","typeName":"System.String"},{"version":1,"name":"pageParam","typeName":"System.Integer"},{"version":1,"name":"pageSize","typeName":"System.Integer"}],"dependents":[]},{"version":1,"name":"setBannerPhoto","modifiers":["public","static"],"typeName":"ConnectApi.BannerPhoto","parameters":[{"version":1,"name":"communityId","typeName":"System.String"},{"version":1,"name":"groupId","typeName":"System.String"},{"version":1,"name":"fileUpload","typeName":"ConnectApi.BinaryInput"}],"dependents":[]},{"version":1,"name":"setBannerPhoto","modifiers":["public","static"],"typeName":"ConnectApi.BannerPhoto","parameters":[{"version":1,"name":"communityId","typeName":"System.String"},{"version":1,"name":"groupId","typeName":"System.String"},{"version":1,"name":"fileId","typeName":"System.String"},{"version":1,"name":"versionNumber","typeName":"System.Integer"}],"dependents":[]},{"version":1,"name":"setBannerPhotoWithAttributes","modifiers":["public","static"],"typeName":"ConnectApi.BannerPhoto","parameters":[{"version":1,"name":"communityId","typeName":"System.String"},{"version":1,"name":"groupId","typeName":"System.String"},{"version":1,"name":"bannerPhoto","typeName":"ConnectApi.BannerPhotoInput"}],"dependents":[]},{"version":1,"name":"setBannerPhotoWithAttributes","modifiers":["public","static"],"typeName":"ConnectApi.BannerPhoto","parameters":[{"version":1,"name":"communityId","typeName":"System.String"},{"version":1,"name":"groupId","typeName":"System.String"},{"version":1,"name":"bannerPhoto","typeName":"ConnectApi.BannerPhotoInput"},{"version":1,"name":"fileUpload","typeName":"ConnectApi.BinaryInput"}],"dependents":[]},{"version":1,"name":"setPhoto","modifiers":["public","static"],"typeName":"ConnectApi.Photo","parameters":[{"version":1,"name":"communityId","typeName":"System.String"},{"version":1,"name":"groupId","typeName":"System.String"},{"version":1,"name":"fileId","typeName":"System.String"},{"version":1,"name":"versionNumber","typeName":"System.Integer"}],"dependents":[]},{"version":1,"name":"setPhoto","modifiers":["public","static"],"typeName":"ConnectApi.Photo","parameters":[{"version":1,"name":"communityId","typeName":"System.String"},{"version":1,"name":"groupId","typeName":"System.String"},{"version":1,"name":"fileUpload","typeName":"ConnectApi.BinaryInput"}],"dependents":[]},{"version":1,"name":"setPhotoWithAttributes","modifiers":["public","static"],"typeName":"ConnectApi.Photo","parameters":[{"version":1,"name":"communityId","typeName":"System.String"},{"version":1,"name":"groupId","typeName":"System.String"},{"version":1,"name":"photo","typeName":"ConnectApi.PhotoInput"}],"dependents":[]},{"version":1,"name":"setPhotoWithAttributes","modifiers":["public","static"],"typeName":"ConnectApi.Photo","parameters":[{"version":1,"name":"communityId","typeName":"System.String"},{"version":1,"name":"groupId","typeName":"System.String"},{"version":1,"name":"photo","typeName":"ConnectApi.PhotoInput"},{"version":1,"name":"fileUpload","typeName":"ConnectApi.BinaryInput"}],"dependents":[]},{"version":1,"name":"setTestSearchGroups","modifiers":["public","static"],"typeName":"void","parameters":[{"version":1,"name":"communityId","typeName":"System.String"},{"version":1,"name":"q","typeName":"System.String"},{"version":1,"name":"archiveStatus","typeName":"ConnectApi.GroupArchiveStatus"},{"version":1,"name":"pageParam","typeName":"System.Integer"},{"version":1,"name":"pageSize","typeName":"System.Integer"},{"version":1,"name":"result","typeName":"ConnectApi.ChatterGroupPage"}],"dependents":[]},{"version":1,"name":"setTestSearchGroups","modifiers":["public","static"],"typeName":"void","parameters":[{"version":1,"name":"communityId","typeName":"System.String"},{"version":1,"name":"q","typeName":"System.String"},{"version":1,"name":"pageParam","typeName":"System.Integer"},{"version":1,"name":"pageSize","typeName":"System.Integer"},{"version":1,"name":"result","typeName":"ConnectApi.ChatterGroupPage"}],"dependents":[]},{"version":1,"name":"setTestSearchGroups","modifiers":["public","static"],"typeName":"void","parameters":[{"version":1,"name":"communityId","typeName":"System.String"},{"version":1,"name":"q","typeName":"System.String"},{"version":1,"name":"result","typeName":"ConnectApi.ChatterGroupPage"}],"dependents":[]},{"version":1,"name":"updateGroup","modifiers":["public","static"],"typeName":"ConnectApi.ChatterGroupDetail","parameters":[{"version":1,"name":"communityId","typeName":"System.String"},{"version":1,"name":"groupId","typeName":"System.String"},{"version":1,"name":"groupInput","typeName":"ConnectApi.ChatterGroupInput"}],"dependents":[]},{"version":1,"name":"updateGroupMember","modifiers":["public","static"],"typeName":"ConnectApi.GroupMember","parameters":[{"version":1,"name":"communityId","typeName":"System.String"},{"version":1,"name":"membershipId","typeName":"System.String"},{"version":1,"name":"role","typeName":"ConnectApi.GroupMembershipType"}],"dependents":[]},{"version":1,"name":"updateMyChatterSettings","modifiers":["public","static"],"typeName":"ConnectApi.GroupChatterSettings","parameters":[{"version":1,"name":"communityId","typeName":"System.String"},{"version":1,"name":"groupId","typeName":"System.String"},{"version":1,"name":"emailFrequency","typeName":"ConnectApi.GroupEmailFrequency"}],"dependents":[]},{"version":1,"name":"updateRequestStatus","modifiers":["public","static"],"typeName":"ConnectApi.GroupMembershipRequest","parameters":[{"version":1,"name":"communityId","typeName":"System.String"},{"version":1,"name":"requestId","typeName":"System.String"},{"version":1,"name":"status","typeName":"ConnectApi.GroupMembershipRequestStatus"}],"dependents":[]},{"version":1,"name":"updateRequestStatus","modifiers":["public","static"],"typeName":"ConnectApi.GroupMembershipRequest","parameters":[{"version":1,"name":"communityId","typeName":"System.String"},{"version":1,"name":"requestId","typeName":"System.String"},{"version":1,"name":"status","typeName":"ConnectApi.GroupMembershipRequestStatus"},{"version":1,"name":"responseMessage","typeName":"System.String"}],"dependents":[]}],"nestedTypes":[],"dependents":[]}