{"version":1,"sourceHash":0,"idRange":[],"name":"WorkflowProcessStatus","typeName":"ConnectApi.WorkflowProcessStatus","nature":"enum","modifiers":["public"],"superClass":"","interfaces":[],"blocks":[],"fields":[{"version":1,"range":[],"name":"Approved","modifiers":["final","public","static"],"typeName":"ConnectApi.WorkflowProcessStatus","readAccess":"public","writeAccess":"public","dependents":[]},{"version":1,"range":[],"name":"Fault","modifiers":["final","public","static"],"typeName":"ConnectApi.WorkflowProcessStatus","readAccess":"public","writeAccess":"public","dependents":[]},{"version":1,"range":[],"name":"Held","modifiers":["final","public","static"],"typeName":"ConnectApi.WorkflowProcessStatus","readAccess":"public","writeAccess":"public","dependents":[]},{"version":1,"range":[],"name":"NoResponse","modifiers":["final","public","static"],"typeName":"ConnectApi.WorkflowProcessStatus","readAccess":"public","writeAccess":"public","dependents":[]},{"version":1,"range":[],"name":"Pending","modifiers":["final","public","static"],"typeName":"ConnectApi.WorkflowProcessStatus","readAccess":"public","writeAccess":"public","dependents":[]},{"version":1,"range":[],"name":"Reassigned","modifiers":["final","public","static"],"typeName":"ConnectApi.WorkflowProcessStatus","readAccess":"public","writeAccess":"public","dependents":[]},{"version":1,"range":[],"name":"Rejected","modifiers":["final","public","static"],"typeName":"ConnectApi.WorkflowProcessStatus","readAccess":"public","writeAccess":"public","dependents":[]},{"version":1,"range":[],"name":"Removed","modifiers":["final","public","static"],"typeName":"ConnectApi.WorkflowProcessStatus","readAccess":"public","writeAccess":"public","dependents":[]},{"version":1,"range":[],"name":"Started","modifiers":["final","public","static"],"typeName":"ConnectApi.WorkflowProcessStatus","readAccess":"public","writeAccess":"public","dependents":[]}],"constructors":[],"methods":[{"version":1,"name":"equals","modifiers":["public"],"typeName":"System.Boolean","parameters":[{"version":1,"name":"other","typeName":"Internal.Object$"}],"dependents":[]},{"version":1,"name":"hashCode","modifiers":["public"],"typeName":"System.Integer","parameters":[],"dependents":[]},{"version":1,"name":"name","modifiers":["public"],"typeName":"System.String","parameters":[],"dependents":[]},{"version":1,"name":"original","modifiers":["public"],"typeName":"System.Integer","parameters":[],"dependents":[]},{"version":1,"name":"values","modifiers":["public","static"],"typeName":"System.List<System.String>","parameters":[],"dependents":[]}],"nestedTypes":[],"dependents":[]}