{"sourceHash":0,"idRange":[],"name":"DescribeSObjectResult","typeName":{"name":{"value":"DescribeSObjectResult"},"outer":[{"name":{"value":"Schema"}}]},"nature":"class","modifiers":["public","virtual"],"superClass":[],"interfaces":[],"blocks":[],"fields":[{"idRange":[],"name":"Accessible","modifiers":["public"],"typeName":{"name":{"value":"Boolean"},"outer":[{"name":{"value":"System"}}]},"readAccess":"public","writeAccess":"public","dependents":[]},{"idRange":[],"name":"ChildRelationships","modifiers":["public"],"typeName":{"name":{"value":"List"},"params":[{"name":{"value":"ChildRelationship"},"outer":[{"name":{"value":"Schema"}}]}],"outer":[{"name":{"value":"System"}}]},"readAccess":"public","writeAccess":"public","dependents":[]},{"idRange":[],"name":"Createable","modifiers":["public"],"typeName":{"name":{"value":"Boolean"},"outer":[{"name":{"value":"System"}}]},"readAccess":"public","writeAccess":"public","dependents":[]},{"idRange":[],"name":"Custom","modifiers":["public"],"typeName":{"name":{"value":"Boolean"},"outer":[{"name":{"value":"System"}}]},"readAccess":"public","writeAccess":"public","dependents":[]},{"idRange":[],"name":"CustomSetting","modifiers":["public"],"typeName":{"name":{"value":"Boolean"},"outer":[{"name":{"value":"System"}}]},"readAccess":"public","writeAccess":"public","dependents":[]},{"idRange":[],"name":"Deletable","modifiers":["public"],"typeName":{"name":{"value":"Boolean"},"outer":[{"name":{"value":"System"}}]},"readAccess":"public","writeAccess":"public","dependents":[]},{"idRange":[],"name":"DeprecatedAndHidden","modifiers":["public"],"typeName":{"name":{"value":"Boolean"},"outer":[{"name":{"value":"System"}}]},"readAccess":"public","writeAccess":"public","dependents":[]},{"idRange":[],"name":"FeedEnabled","modifiers":["public"],"typeName":{"name":{"value":"Boolean"},"outer":[{"name":{"value":"System"}}]},"readAccess":"public","writeAccess":"public","dependents":[]},{"idRange":[],"name":"FieldSets","modifiers":["public"],"typeName":{"name":{"value":"SObjectTypeFieldSets"},"outer":[{"name":{"value":"Schema"}}]},"readAccess":"public","writeAccess":"public","dependents":[]},{"idRange":[],"name":"Fields","modifiers":["public"],"typeName":{"name":{"value":"SObjectTypeFields"},"outer":[{"name":{"value":"Schema"}}]},"readAccess":"public","writeAccess":"public","dependents":[]},{"idRange":[],"name":"HasSubtypes","modifiers":["public"],"typeName":{"name":{"value":"Boolean"},"outer":[{"name":{"value":"System"}}]},"readAccess":"public","writeAccess":"public","dependents":[]},{"idRange":[],"name":"IsSubtype","modifiers":["public"],"typeName":{"name":{"value":"Boolean"},"outer":[{"name":{"value":"System"}}]},"readAccess":"public","writeAccess":"public","dependents":[]},{"idRange":[],"name":"KeyPrefix","modifiers":["public"],"typeName":{"name":{"value":"String"},"outer":[{"name":{"value":"System"}}]},"readAccess":"public","writeAccess":"public","dependents":[]},{"idRange":[],"name":"Label","modifiers":["public"],"typeName":{"name":{"value":"String"},"outer":[{"name":{"value":"System"}}]},"readAccess":"public","writeAccess":"public","dependents":[]},{"idRange":[],"name":"LabelPlural","modifiers":["public"],"typeName":{"name":{"value":"String"},"outer":[{"name":{"value":"System"}}]},"readAccess":"public","writeAccess":"public","dependents":[]},{"idRange":[],"name":"LocalName","modifiers":["public"],"typeName":{"name":{"value":"String"},"outer":[{"name":{"value":"System"}}]},"readAccess":"public","writeAccess":"public","dependents":[]},{"idRange":[],"name":"Mergeable","modifiers":["public"],"typeName":{"name":{"value":"Boolean"},"outer":[{"name":{"value":"System"}}]},"readAccess":"public","writeAccess":"public","dependents":[]},{"idRange":[],"name":"MruEnabled","modifiers":["public"],"typeName":{"name":{"value":"Boolean"},"outer":[{"name":{"value":"System"}}]},"readAccess":"public","writeAccess":"public","dependents":[]},{"idRange":[],"name":"Name","modifiers":["public"],"typeName":{"name":{"value":"String"},"outer":[{"name":{"value":"System"}}]},"readAccess":"public","writeAccess":"public","dependents":[]},{"idRange":[],"name":"Queryable","modifiers":["public"],"typeName":{"name":{"value":"Boolean"},"outer":[{"name":{"value":"System"}}]},"readAccess":"public","writeAccess":"public","dependents":[]},{"idRange":[],"name":"RecordTypeInfos","modifiers":["public"],"typeName":{"name":{"value":"List"},"params":[{"name":{"value":"RecordTypeInfo"},"outer":[{"name":{"value":"Schema"}}]}],"outer":[{"name":{"value":"System"}}]},"readAccess":"public","writeAccess":"public","dependents":[]},{"idRange":[],"name":"RecordTypeInfosByDeveloperName","modifiers":["public"],"typeName":{"name":{"value":"Map"},"params":[{"name":{"value":"String"},"outer":[{"name":{"value":"System"}}]},{"name":{"value":"RecordTypeInfo"},"outer":[{"name":{"value":"Schema"}}]}],"outer":[{"name":{"value":"System"}}]},"readAccess":"public","writeAccess":"public","dependents":[]},{"idRange":[],"name":"RecordTypeInfosById","modifiers":["public"],"typeName":{"name":{"value":"Map"},"params":[{"name":{"value":"Id"},"outer":[{"name":{"value":"System"}}]},{"name":{"value":"RecordTypeInfo"},"outer":[{"name":{"value":"Schema"}}]}],"outer":[{"name":{"value":"System"}}]},"readAccess":"public","writeAccess":"public","dependents":[]},{"idRange":[],"name":"RecordTypeInfosByName","modifiers":["public"],"typeName":{"name":{"value":"Map"},"params":[{"name":{"value":"String"},"outer":[{"name":{"value":"System"}}]},{"name":{"value":"RecordTypeInfo"},"outer":[{"name":{"value":"Schema"}}]}],"outer":[{"name":{"value":"System"}}]},"readAccess":"public","writeAccess":"public","dependents":[]},{"idRange":[],"name":"SObjectType","modifiers":["public"],"typeName":{"name":{"value":"SObjectType"},"outer":[{"name":{"value":"Schema"}}]},"readAccess":"public","writeAccess":"public","dependents":[]},{"idRange":[],"name":"Searchable","modifiers":["public"],"typeName":{"name":{"value":"Boolean"},"outer":[{"name":{"value":"System"}}]},"readAccess":"public","writeAccess":"public","dependents":[]},{"idRange":[],"name":"Undeletable","modifiers":["public"],"typeName":{"name":{"value":"Boolean"},"outer":[{"name":{"value":"System"}}]},"readAccess":"public","writeAccess":"public","dependents":[]},{"idRange":[],"name":"Updateable","modifiers":["public"],"typeName":{"name":{"value":"Boolean"},"outer":[{"name":{"value":"System"}}]},"readAccess":"public","writeAccess":"public","dependents":[]}],"constructors":[{"idRange":[],"modifiers":["public"],"parameters":[],"dependents":[]}],"methods":[{"idRange":[],"name":"getChildRelationships","modifiers":["public"],"typeName":{"name":{"value":"List"},"params":[{"name":{"value":"ChildRelationship"},"outer":[{"name":{"value":"Schema"}}]}],"outer":[{"name":{"value":"System"}}]},"parameters":[],"dependents":[]},{"idRange":[],"name":"getFieldSets","modifiers":["public"],"typeName":{"name":{"value":"SObjectTypeFieldSets"},"outer":[{"name":{"value":"Schema"}}]},"parameters":[],"dependents":[]},{"idRange":[],"name":"getFields","modifiers":["public"],"typeName":{"name":{"value":"SObjectTypeFields"},"outer":[{"name":{"value":"Schema"}}]},"parameters":[],"dependents":[]},{"idRange":[],"name":"getHasSubtypes","modifiers":["public"],"typeName":{"name":{"value":"Boolean"},"outer":[{"name":{"value":"System"}}]},"parameters":[],"dependents":[]},{"idRange":[],"name":"getIsSubtype","modifiers":["public"],"typeName":{"name":{"value":"Boolean"},"outer":[{"name":{"value":"System"}}]},"parameters":[],"dependents":[]},{"idRange":[],"name":"getKeyPrefix","modifiers":["public"],"typeName":{"name":{"value":"String"},"outer":[{"name":{"value":"System"}}]},"parameters":[],"dependents":[]},{"idRange":[],"name":"getLabel","modifiers":["public"],"typeName":{"name":{"value":"String"},"outer":[{"name":{"value":"System"}}]},"parameters":[],"dependents":[]},{"idRange":[],"name":"getLabelPlural","modifiers":["public"],"typeName":{"name":{"value":"String"},"outer":[{"name":{"value":"System"}}]},"parameters":[],"dependents":[]},{"idRange":[],"name":"getLocalName","modifiers":["public"],"typeName":{"name":{"value":"String"},"outer":[{"name":{"value":"System"}}]},"parameters":[],"dependents":[]},{"idRange":[],"name":"getName","modifiers":["public"],"typeName":{"name":{"value":"String"},"outer":[{"name":{"value":"System"}}]},"parameters":[],"dependents":[]},{"idRange":[],"name":"getRecordTypeInfos","modifiers":["public"],"typeName":{"name":{"value":"List"},"params":[{"name":{"value":"RecordTypeInfo"},"outer":[{"name":{"value":"Schema"}}]}],"outer":[{"name":{"value":"System"}}]},"parameters":[],"dependents":[]},{"idRange":[],"name":"getRecordTypeInfosByDeveloperName","modifiers":["public"],"typeName":{"name":{"value":"Map"},"params":[{"name":{"value":"String"},"outer":[{"name":{"value":"System"}}]},{"name":{"value":"RecordTypeInfo"},"outer":[{"name":{"value":"Schema"}}]}],"outer":[{"name":{"value":"System"}}]},"parameters":[],"dependents":[]},{"idRange":[],"name":"getRecordTypeInfosById","modifiers":["public"],"typeName":{"name":{"value":"Map"},"params":[{"name":{"value":"Id"},"outer":[{"name":{"value":"System"}}]},{"name":{"value":"RecordTypeInfo"},"outer":[{"name":{"value":"Schema"}}]}],"outer":[{"name":{"value":"System"}}]},"parameters":[],"dependents":[]},{"idRange":[],"name":"getRecordTypeInfosByName","modifiers":["public"],"typeName":{"name":{"value":"Map"},"params":[{"name":{"value":"String"},"outer":[{"name":{"value":"System"}}]},{"name":{"value":"RecordTypeInfo"},"outer":[{"name":{"value":"Schema"}}]}],"outer":[{"name":{"value":"System"}}]},"parameters":[],"dependents":[]},{"idRange":[],"name":"getSObjectType","modifiers":["public"],"typeName":{"name":{"value":"SObjectType"},"outer":[{"name":{"value":"Schema"}}]},"parameters":[],"dependents":[]},{"idRange":[],"name":"isAccessible","modifiers":["public"],"typeName":{"name":{"value":"Boolean"},"outer":[{"name":{"value":"System"}}]},"parameters":[],"dependents":[]},{"idRange":[],"name":"isCreateable","modifiers":["public"],"typeName":{"name":{"value":"Boolean"},"outer":[{"name":{"value":"System"}}]},"parameters":[],"dependents":[]},{"idRange":[],"name":"isCustom","modifiers":["public"],"typeName":{"name":{"value":"Boolean"},"outer":[{"name":{"value":"System"}}]},"parameters":[],"dependents":[]},{"idRange":[],"name":"isCustomSetting","modifiers":["public"],"typeName":{"name":{"value":"Boolean"},"outer":[{"name":{"value":"System"}}]},"parameters":[],"dependents":[]},{"idRange":[],"name":"isDeletable","modifiers":["public"],"typeName":{"name":{"value":"Boolean"},"outer":[{"name":{"value":"System"}}]},"parameters":[],"dependents":[]},{"idRange":[],"name":"isDeprecatedAndHidden","modifiers":["public"],"typeName":{"name":{"value":"Boolean"},"outer":[{"name":{"value":"System"}}]},"parameters":[],"dependents":[]},{"idRange":[],"name":"isFeedEnabled","modifiers":["public"],"typeName":{"name":{"value":"Boolean"},"outer":[{"name":{"value":"System"}}]},"parameters":[],"dependents":[]},{"idRange":[],"name":"isMergeable","modifiers":["public"],"typeName":{"name":{"value":"Boolean"},"outer":[{"name":{"value":"System"}}]},"parameters":[],"dependents":[]},{"idRange":[],"name":"isMruEnabled","modifiers":["public"],"typeName":{"name":{"value":"Boolean"},"outer":[{"name":{"value":"System"}}]},"parameters":[],"dependents":[]},{"idRange":[],"name":"isQueryable","modifiers":["public"],"typeName":{"name":{"value":"Boolean"},"outer":[{"name":{"value":"System"}}]},"parameters":[],"dependents":[]},{"idRange":[],"name":"isSearchable","modifiers":["public"],"typeName":{"name":{"value":"Boolean"},"outer":[{"name":{"value":"System"}}]},"parameters":[],"dependents":[]},{"idRange":[],"name":"isUndeletable","modifiers":["public"],"typeName":{"name":{"value":"Boolean"},"outer":[{"name":{"value":"System"}}]},"parameters":[],"dependents":[]},{"idRange":[],"name":"isUpdateable","modifiers":["public"],"typeName":{"name":{"value":"Boolean"},"outer":[{"name":{"value":"System"}}]},"parameters":[],"dependents":[]}],"nestedTypes":[],"dependents":[],"holders":[]}