{"sourceHash":0,"idRange":[],"name":"DMLOptions","typeName":{"name":{"value":"DMLOptions"},"outer":[{"name":{"value":"Database"}}]},"nature":"class","modifiers":["public","virtual"],"superClass":[],"interfaces":[],"blocks":[],"fields":[{"idRange":[],"name":"AllowFieldTruncation","modifiers":["public"],"typeName":{"name":{"value":"Boolean"},"outer":[{"name":{"value":"System"}}]},"readAccess":"public","writeAccess":"public","dependents":[]},{"idRange":[],"name":"AssignmentRuleHeader","modifiers":["public"],"typeName":{"name":{"value":"AssignmentRuleHeader"},"outer":[{"name":{"value":"DMLOptions"},"outer":[{"name":{"value":"Database"}}]}]},"readAccess":"public","writeAccess":"public","dependents":[]},{"idRange":[],"name":"DuplicateRuleHeader","modifiers":["public"],"typeName":{"name":{"value":"DuplicateRuleHeader"},"outer":[{"name":{"value":"DMLOptions"},"outer":[{"name":{"value":"Database"}}]}]},"readAccess":"public","writeAccess":"public","dependents":[]},{"idRange":[],"name":"EmailHeader","modifiers":["public"],"typeName":{"name":{"value":"EmailHeader"},"outer":[{"name":{"value":"DMLOptions"},"outer":[{"name":{"value":"Database"}}]}]},"readAccess":"public","writeAccess":"public","dependents":[]},{"idRange":[],"name":"LocaleOptions","modifiers":["public"],"typeName":{"name":{"value":"String"},"outer":[{"name":{"value":"System"}}]},"readAccess":"public","writeAccess":"public","dependents":[]},{"idRange":[],"name":"OptAllOrNone","modifiers":["public"],"typeName":{"name":{"value":"Boolean"},"outer":[{"name":{"value":"System"}}]},"readAccess":"public","writeAccess":"public","dependents":[]}],"constructors":[{"idRange":[],"modifiers":["public"],"parameters":[],"dependents":[]}],"methods":[],"nestedTypes":[{"sourceHash":0,"idRange":[],"name":"AssignmentRuleHeader","typeName":{"name":{"value":"AssignmentRuleHeader"},"outer":[{"name":{"value":"DMLOptions"},"outer":[{"name":{"value":"Database"}}]}]},"nature":"class","modifiers":["public","static","virtual"],"superClass":[],"interfaces":[],"blocks":[],"fields":[{"idRange":[],"name":"AssignmentRuleId","modifiers":["public"],"typeName":{"name":{"value":"Id"},"outer":[{"name":{"value":"System"}}]},"readAccess":"public","writeAccess":"public","dependents":[]},{"idRange":[],"name":"UseDefaultRule","modifiers":["public"],"typeName":{"name":{"value":"Boolean"},"outer":[{"name":{"value":"System"}}]},"readAccess":"public","writeAccess":"public","dependents":[]}],"constructors":[{"idRange":[],"modifiers":["public"],"parameters":[],"dependents":[]}],"methods":[],"nestedTypes":[],"dependents":[],"holders":[]},{"sourceHash":0,"idRange":[],"name":"DuplicateRuleHeader","typeName":{"name":{"value":"DuplicateRuleHeader"},"outer":[{"name":{"value":"DMLOptions"},"outer":[{"name":{"value":"Database"}}]}]},"nature":"class","modifiers":["public","static","virtual"],"superClass":[],"interfaces":[],"blocks":[],"fields":[{"idRange":[],"name":"AllowSave","modifiers":["public"],"typeName":{"name":{"value":"Boolean"},"outer":[{"name":{"value":"System"}}]},"readAccess":"public","writeAccess":"public","dependents":[]},{"idRange":[],"name":"RunAsCurrentUser","modifiers":["public"],"typeName":{"name":{"value":"Boolean"},"outer":[{"name":{"value":"System"}}]},"readAccess":"public","writeAccess":"public","dependents":[]}],"constructors":[{"idRange":[],"modifiers":["public"],"parameters":[],"dependents":[]}],"methods":[],"nestedTypes":[],"dependents":[],"holders":[]},{"sourceHash":0,"idRange":[],"name":"EmailHeader","typeName":{"name":{"value":"EmailHeader"},"outer":[{"name":{"value":"DMLOptions"},"outer":[{"name":{"value":"Database"}}]}]},"nature":"class","modifiers":["public","static","virtual"],"superClass":[],"interfaces":[],"blocks":[],"fields":[{"idRange":[],"name":"TriggerAutoResponseEmail","modifiers":["public"],"typeName":{"name":{"value":"Boolean"},"outer":[{"name":{"value":"System"}}]},"readAccess":"public","writeAccess":"public","dependents":[]},{"idRange":[],"name":"TriggerOtherEmail","modifiers":["public"],"typeName":{"name":{"value":"Boolean"},"outer":[{"name":{"value":"System"}}]},"readAccess":"public","writeAccess":"public","dependents":[]},{"idRange":[],"name":"TriggerUserEmail","modifiers":["public"],"typeName":{"name":{"value":"Boolean"},"outer":[{"name":{"value":"System"}}]},"readAccess":"public","writeAccess":"public","dependents":[]}],"constructors":[{"idRange":[],"modifiers":["public"],"parameters":[],"dependents":[]}],"methods":[],"nestedTypes":[],"dependents":[],"holders":[]}],"dependents":[],"holders":[]}