{"sourceHash":0,"idRange":[],"name":"DuplicateError","typeName":{"$type":"TypeName","name":{"value":"DuplicateError"},"outer":[{"$type":"TypeName","name":{"value":"Database"}}]},"nature":"class","modifiers":["public","virtual"],"superClass":[],"interfaces":[],"blocks":[],"fields":[{"idRange":[],"name":"DuplicateResult","modifiers":["public"],"typeName":{"$type":"TypeName","name":{"value":"DuplicateResult"},"outer":[{"$type":"TypeName","name":{"value":"Datacloud"}}]},"readAccess":"public","writeAccess":"public","dependents":[]}],"constructors":[{"idRange":[],"modifiers":["public"],"parameters":[],"dependents":[]}],"methods":[{"idRange":[],"name":"getDuplicateResult","modifiers":["public"],"typeName":{"$type":"TypeName","name":{"value":"DuplicateResult"},"outer":[{"$type":"TypeName","name":{"value":"Datacloud"}}]},"parameters":[],"dependents":[]},{"idRange":[],"name":"getFields","modifiers":["public"],"typeName":{"$type":"TypeName","name":{"value":"List"},"params":[{"$type":"TypeName","name":{"value":"String"},"outer":[{"$type":"TypeName","name":{"value":"System"}}]}],"outer":[{"$type":"TypeName","name":{"value":"System"}}]},"parameters":[],"dependents":[]},{"idRange":[],"name":"getMessage","modifiers":["public"],"typeName":{"$type":"TypeName","name":{"value":"String"},"outer":[{"$type":"TypeName","name":{"value":"System"}}]},"parameters":[],"dependents":[]},{"idRange":[],"name":"getStatusCode","modifiers":["public"],"typeName":{"$type":"TypeName","name":{"value":"StatusCode"},"outer":[{"$type":"TypeName","name":{"value":"System"}}]},"parameters":[],"dependents":[]}],"nestedTypes":[],"dependents":[],"holders":[]}