{"sourceHash":0,"idRange":[],"name":"QuickActionDefaults","typeName":{"name":{"value":"QuickActionDefaults"},"outer":[{"name":{"value":"QuickAction"}}]},"nature":"class","modifiers":["public","virtual"],"superClass":[],"interfaces":[],"blocks":[],"fields":[],"constructors":[{"idRange":[],"modifiers":["public"],"parameters":[],"dependents":[]}],"methods":[{"idRange":[],"name":"getActionName","modifiers":["public"],"typeName":{"name":{"value":"String"},"outer":[{"name":{"value":"System"}}]},"parameters":[],"dependents":[]},{"idRange":[],"name":"getActionType","modifiers":["public"],"typeName":{"name":{"value":"String"},"outer":[{"name":{"value":"System"}}]},"parameters":[],"dependents":[]},{"idRange":[],"name":"getContextId","modifiers":["public"],"typeName":{"name":{"value":"Id"},"outer":[{"name":{"value":"System"}}]},"parameters":[],"dependents":[]},{"idRange":[],"name":"getTargetSObject","modifiers":["public"],"typeName":{"name":{"value":"SObject"},"outer":[{"name":{"value":"System"}}]},"parameters":[],"dependents":[]}],"nestedTypes":[],"dependents":[],"holders":[]}