{"sourceHash":0,"idRange":[],"name":"SelfRegisterController","typeName":{"name":{"value":"SelfRegisterController"},"outer":[{"name":{"value":"applauncher"}}]},"nature":"class","modifiers":["public","virtual"],"superClass":[],"interfaces":[],"blocks":[],"fields":[],"constructors":[{"idRange":[],"modifiers":["public"],"parameters":[],"dependents":[]}],"methods":[{"idRange":[],"name":"getExtraFields","modifiers":["public","static"],"typeName":{"name":{"value":"List"},"params":[{"name":{"value":"Map"},"params":[{"name":{"value":"String"},"outer":[{"name":{"value":"System"}}]},{"name":{"value":"Object$"},"outer":[{"name":{"value":"Internal"}}]}],"outer":[{"name":{"value":"System"}}]}],"outer":[{"name":{"value":"System"}}]},"parameters":[{"name":"extraFieldsFieldSet","typeName":{"name":{"value":"String"},"outer":[{"name":{"value":"System"}}]}}],"dependents":[]},{"idRange":[],"name":"isValidPassword","modifiers":["public","static"],"typeName":{"name":{"value":"Boolean"},"outer":[{"name":{"value":"System"}}]},"parameters":[{"name":"password","typeName":{"name":{"value":"String"},"outer":[{"name":{"value":"System"}}]}},{"name":"confirmPassword","typeName":{"name":{"value":"String"},"outer":[{"name":{"value":"System"}}]}}],"dependents":[]},{"idRange":[],"name":"selfRegister","modifiers":["public","static"],"typeName":{"name":{"value":"String"},"outer":[{"name":{"value":"System"}}]},"parameters":[{"name":"firstname","typeName":{"name":{"value":"String"},"outer":[{"name":{"value":"System"}}]}},{"name":"lastname","typeName":{"name":{"value":"String"},"outer":[{"name":{"value":"System"}}]}},{"name":"email","typeName":{"name":{"value":"String"},"outer":[{"name":{"value":"System"}}]}},{"name":"password","typeName":{"name":{"value":"String"},"outer":[{"name":{"value":"System"}}]}},{"name":"confirmPassword","typeName":{"name":{"value":"String"},"outer":[{"name":{"value":"System"}}]}},{"name":"accountId","typeName":{"name":{"value":"String"},"outer":[{"name":{"value":"System"}}]}},{"name":"regConfirmUrl","typeName":{"name":{"value":"String"},"outer":[{"name":{"value":"System"}}]}},{"name":"extraFields","typeName":{"name":{"value":"String"},"outer":[{"name":{"value":"System"}}]}},{"name":"startUrl","typeName":{"name":{"value":"String"},"outer":[{"name":{"value":"System"}}]}},{"name":"includePassword","typeName":{"name":{"value":"Boolean"},"outer":[{"name":{"value":"System"}}]}}],"dependents":[]},{"idRange":[],"name":"setExperienceId","modifiers":["public","static"],"typeName":{"name":{"value":"String"},"outer":[{"name":{"value":"System"}}]},"parameters":[{"name":"expId","typeName":{"name":{"value":"String"},"outer":[{"name":{"value":"System"}}]}}],"dependents":[]}],"nestedTypes":[],"dependents":[],"holders":[]}