{"version":1,"name":"ApplicationReadWriteMode","typeName":"System.ApplicationReadWriteMode","nature":"enum","modifiers":["public"],"superClass":"","interfaces":[],"fields":[{"version":1,"name":"DEFAULT","modifiers":["final","public","static"],"typeName":"System.ApplicationReadWriteMode","readAccess":"public","writeAccess":"public"},{"version":1,"name":"READ_ONLY","modifiers":["final","public","static"],"typeName":"System.ApplicationReadWriteMode","readAccess":"public","writeAccess":"public"}],"constructors":[],"methods":[{"version":1,"name":"equals","modifiers":["public"],"typeName":"System.Boolean","parameters":[{"version":1,"name":"other","typeName":"Object"}]},{"version":1,"name":"hashCode","modifiers":["public"],"typeName":"System.Integer","parameters":[]},{"version":1,"name":"name","modifiers":["public"],"typeName":"System.String","parameters":[]},{"version":1,"name":"original","modifiers":["public"],"typeName":"System.Integer","parameters":[]},{"version":1,"name":"values","modifiers":["public","static"],"typeName":"System.List<System.String>","parameters":[]}],"nestedTypes":[]}