{"sourceHash":0,"idRange":[],"name":"Crypto","typeName":{"name":{"value":"Crypto"},"outer":[{"name":{"value":"System"}}]},"nature":"class","modifiers":["public","virtual"],"superClass":[],"interfaces":[],"blocks":[],"fields":[],"constructors":[{"idRange":[],"modifiers":["public"],"parameters":[],"dependents":[]}],"methods":[{"idRange":[],"name":"decrypt","modifiers":["public","static"],"typeName":{"name":{"value":"Blob"},"outer":[{"name":{"value":"System"}}]},"parameters":[{"name":"algorithmName","typeName":{"name":{"value":"String"},"outer":[{"name":{"value":"System"}}]}},{"name":"secretKey","typeName":{"name":{"value":"Blob"},"outer":[{"name":{"value":"System"}}]}},{"name":"initializationVector","typeName":{"name":{"value":"Blob"},"outer":[{"name":{"value":"System"}}]}},{"name":"encryptedData","typeName":{"name":{"value":"Blob"},"outer":[{"name":{"value":"System"}}]}}],"dependents":[]},{"idRange":[],"name":"decryptWithManagedIV","modifiers":["public","static"],"typeName":{"name":{"value":"Blob"},"outer":[{"name":{"value":"System"}}]},"parameters":[{"name":"algorithmName","typeName":{"name":{"value":"String"},"outer":[{"name":{"value":"System"}}]}},{"name":"secretKey","typeName":{"name":{"value":"Blob"},"outer":[{"name":{"value":"System"}}]}},{"name":"encryptedData","typeName":{"name":{"value":"Blob"},"outer":[{"name":{"value":"System"}}]}}],"dependents":[]},{"idRange":[],"name":"encrypt","modifiers":["public","static"],"typeName":{"name":{"value":"Blob"},"outer":[{"name":{"value":"System"}}]},"parameters":[{"name":"algorithmName","typeName":{"name":{"value":"String"},"outer":[{"name":{"value":"System"}}]}},{"name":"secretKey","typeName":{"name":{"value":"Blob"},"outer":[{"name":{"value":"System"}}]}},{"name":"initializationVector","typeName":{"name":{"value":"Blob"},"outer":[{"name":{"value":"System"}}]}},{"name":"clearData","typeName":{"name":{"value":"Blob"},"outer":[{"name":{"value":"System"}}]}}],"dependents":[]},{"idRange":[],"name":"encryptWithManagedIV","modifiers":["public","static"],"typeName":{"name":{"value":"Blob"},"outer":[{"name":{"value":"System"}}]},"parameters":[{"name":"algorithmName","typeName":{"name":{"value":"String"},"outer":[{"name":{"value":"System"}}]}},{"name":"secretKey","typeName":{"name":{"value":"Blob"},"outer":[{"name":{"value":"System"}}]}},{"name":"clearData","typeName":{"name":{"value":"Blob"},"outer":[{"name":{"value":"System"}}]}}],"dependents":[]},{"idRange":[],"name":"generateAesKey","modifiers":["public","static"],"typeName":{"name":{"value":"Blob"},"outer":[{"name":{"value":"System"}}]},"parameters":[{"name":"size","typeName":{"name":{"value":"Integer"},"outer":[{"name":{"value":"System"}}]}}],"dependents":[]},{"idRange":[],"name":"generateDigest","modifiers":["public","static"],"typeName":{"name":{"value":"Blob"},"outer":[{"name":{"value":"System"}}]},"parameters":[{"name":"algorithmName","typeName":{"name":{"value":"String"},"outer":[{"name":{"value":"System"}}]}},{"name":"input","typeName":{"name":{"value":"Blob"},"outer":[{"name":{"value":"System"}}]}}],"dependents":[]},{"idRange":[],"name":"generateMac","modifiers":["public","static"],"typeName":{"name":{"value":"Blob"},"outer":[{"name":{"value":"System"}}]},"parameters":[{"name":"algorithmName","typeName":{"name":{"value":"String"},"outer":[{"name":{"value":"System"}}]}},{"name":"input","typeName":{"name":{"value":"Blob"},"outer":[{"name":{"value":"System"}}]}},{"name":"privateKey","typeName":{"name":{"value":"Blob"},"outer":[{"name":{"value":"System"}}]}}],"dependents":[]},{"idRange":[],"name":"getRandomInteger","modifiers":["public","static"],"typeName":{"name":{"value":"Integer"},"outer":[{"name":{"value":"System"}}]},"parameters":[],"dependents":[]},{"idRange":[],"name":"getRandomLong","modifiers":["public","static"],"typeName":{"name":{"value":"Long"},"outer":[{"name":{"value":"System"}}]},"parameters":[],"dependents":[]},{"idRange":[],"name":"sign","modifiers":["public","static"],"typeName":{"name":{"value":"Blob"},"outer":[{"name":{"value":"System"}}]},"parameters":[{"name":"algorithmName","typeName":{"name":{"value":"String"},"outer":[{"name":{"value":"System"}}]}},{"name":"input","typeName":{"name":{"value":"Blob"},"outer":[{"name":{"value":"System"}}]}},{"name":"privateKey","typeName":{"name":{"value":"Blob"},"outer":[{"name":{"value":"System"}}]}}],"dependents":[]},{"idRange":[],"name":"signWithCertificate","modifiers":["public","static"],"typeName":{"name":{"value":"Blob"},"outer":[{"name":{"value":"System"}}]},"parameters":[{"name":"algorithmName","typeName":{"name":{"value":"String"},"outer":[{"name":{"value":"System"}}]}},{"name":"input","typeName":{"name":{"value":"Blob"},"outer":[{"name":{"value":"System"}}]}},{"name":"certDevName","typeName":{"name":{"value":"String"},"outer":[{"name":{"value":"System"}}]}}],"dependents":[]},{"idRange":[],"name":"signXml","modifiers":["public","static"],"typeName":{"name":{"value":"void"}},"parameters":[{"name":"algorithmName","typeName":{"name":{"value":"String"},"outer":[{"name":{"value":"System"}}]}},{"name":"node","typeName":{"name":{"value":"XmlNode"},"outer":[{"name":{"value":"dom"}}]}},{"name":"idAttributeName","typeName":{"name":{"value":"String"},"outer":[{"name":{"value":"System"}}]}},{"name":"certDevName","typeName":{"name":{"value":"String"},"outer":[{"name":{"value":"System"}}]}}],"dependents":[]},{"idRange":[],"name":"signXml","modifiers":["public","static"],"typeName":{"name":{"value":"void"}},"parameters":[{"name":"algorithmName","typeName":{"name":{"value":"String"},"outer":[{"name":{"value":"System"}}]}},{"name":"node","typeName":{"name":{"value":"XmlNode"},"outer":[{"name":{"value":"dom"}}]}},{"name":"idAttributeName","typeName":{"name":{"value":"String"},"outer":[{"name":{"value":"System"}}]}},{"name":"certDevName","typeName":{"name":{"value":"String"},"outer":[{"name":{"value":"System"}}]}},{"name":"refChild","typeName":{"name":{"value":"XmlNode"},"outer":[{"name":{"value":"dom"}}]}}],"dependents":[]},{"idRange":[],"name":"verify","modifiers":["public","static"],"typeName":{"name":{"value":"Boolean"},"outer":[{"name":{"value":"System"}}]},"parameters":[{"name":"algorithmName","typeName":{"name":{"value":"String"},"outer":[{"name":{"value":"System"}}]}},{"name":"data","typeName":{"name":{"value":"Blob"},"outer":[{"name":{"value":"System"}}]}},{"name":"signature","typeName":{"name":{"value":"Blob"},"outer":[{"name":{"value":"System"}}]}},{"name":"certDevName","typeName":{"name":{"value":"String"},"outer":[{"name":{"value":"System"}}]}}],"dependents":[]},{"idRange":[],"name":"verify","modifiers":["public","static"],"typeName":{"name":{"value":"Boolean"},"outer":[{"name":{"value":"System"}}]},"parameters":[{"name":"algorithmName","typeName":{"name":{"value":"String"},"outer":[{"name":{"value":"System"}}]}},{"name":"data","typeName":{"name":{"value":"Blob"},"outer":[{"name":{"value":"System"}}]}},{"name":"signature","typeName":{"name":{"value":"Blob"},"outer":[{"name":{"value":"System"}}]}},{"name":"publicKey","typeName":{"name":{"value":"Blob"},"outer":[{"name":{"value":"System"}}]}}],"dependents":[]},{"idRange":[],"name":"verifyHmac","modifiers":["public","static"],"typeName":{"name":{"value":"Boolean"},"outer":[{"name":{"value":"System"}}]},"parameters":[{"name":"algorithmName","typeName":{"name":{"value":"String"},"outer":[{"name":{"value":"System"}}]}},{"name":"data","typeName":{"name":{"value":"Blob"},"outer":[{"name":{"value":"System"}}]}},{"name":"privateKey","typeName":{"name":{"value":"Blob"},"outer":[{"name":{"value":"System"}}]}},{"name":"hmacToVerify","typeName":{"name":{"value":"Blob"},"outer":[{"name":{"value":"System"}}]}}],"dependents":[]}],"nestedTypes":[],"dependents":[],"holders":[]}