{"sourceHash":0,"idRange":[],"name":"TriggerOperation","typeName":{"name":{"value":"TriggerOperation"},"params":[],"outer":[{"name":{"value":"System"},"params":[],"outer":[]}]},"nature":"enum","modifiers":["public"],"superClass":[],"interfaces":[],"blocks":[],"fields":[{"idRange":[],"name":"AFTER_DELETE","modifiers":["final","public","static"],"typeName":{"name":{"value":"TriggerOperation"},"params":[],"outer":[{"name":{"value":"System"},"params":[],"outer":[]}]},"readAccess":"public","writeAccess":"public","dependents":[]},{"idRange":[],"name":"AFTER_INSERT","modifiers":["final","public","static"],"typeName":{"name":{"value":"TriggerOperation"},"params":[],"outer":[{"name":{"value":"System"},"params":[],"outer":[]}]},"readAccess":"public","writeAccess":"public","dependents":[]},{"idRange":[],"name":"AFTER_UNDELETE","modifiers":["final","public","static"],"typeName":{"name":{"value":"TriggerOperation"},"params":[],"outer":[{"name":{"value":"System"},"params":[],"outer":[]}]},"readAccess":"public","writeAccess":"public","dependents":[]},{"idRange":[],"name":"AFTER_UPDATE","modifiers":["final","public","static"],"typeName":{"name":{"value":"TriggerOperation"},"params":[],"outer":[{"name":{"value":"System"},"params":[],"outer":[]}]},"readAccess":"public","writeAccess":"public","dependents":[]},{"idRange":[],"name":"BEFORE_DELETE","modifiers":["final","public","static"],"typeName":{"name":{"value":"TriggerOperation"},"params":[],"outer":[{"name":{"value":"System"},"params":[],"outer":[]}]},"readAccess":"public","writeAccess":"public","dependents":[]},{"idRange":[],"name":"BEFORE_INSERT","modifiers":["final","public","static"],"typeName":{"name":{"value":"TriggerOperation"},"params":[],"outer":[{"name":{"value":"System"},"params":[],"outer":[]}]},"readAccess":"public","writeAccess":"public","dependents":[]},{"idRange":[],"name":"BEFORE_UPDATE","modifiers":["final","public","static"],"typeName":{"name":{"value":"TriggerOperation"},"params":[],"outer":[{"name":{"value":"System"},"params":[],"outer":[]}]},"readAccess":"public","writeAccess":"public","dependents":[]}],"constructors":[],"methods":[{"idRange":[],"name":"equals","modifiers":["public"],"typeName":{"name":{"value":"Boolean"},"params":[],"outer":[{"name":{"value":"System"},"params":[],"outer":[]}]},"parameters":[{"name":"other","typeName":{"name":{"value":"Object$"},"params":[],"outer":[{"name":{"value":"Internal"},"params":[],"outer":[]}]}}],"dependents":[]},{"idRange":[],"name":"hashCode","modifiers":["public"],"typeName":{"name":{"value":"Integer"},"params":[],"outer":[{"name":{"value":"System"},"params":[],"outer":[]}]},"parameters":[],"dependents":[]},{"idRange":[],"name":"name","modifiers":["public"],"typeName":{"name":{"value":"String"},"params":[],"outer":[{"name":{"value":"System"},"params":[],"outer":[]}]},"parameters":[],"dependents":[]},{"idRange":[],"name":"original","modifiers":["public"],"typeName":{"name":{"value":"Integer"},"params":[],"outer":[{"name":{"value":"System"},"params":[],"outer":[]}]},"parameters":[],"dependents":[]},{"idRange":[],"name":"values","modifiers":["public","static"],"typeName":{"name":{"value":"List"},"params":[{"name":{"value":"String"},"params":[],"outer":[{"name":{"value":"System"},"params":[],"outer":[]}]}],"outer":[{"name":{"value":"System"},"params":[],"outer":[]}]},"parameters":[],"dependents":[]}],"nestedTypes":[],"dependents":[]}