{"version":1,"sourceHash":0,"idRange":[],"name":"MassEmailMessage","typeName":"Messaging.MassEmailMessage","nature":"class","modifiers":["public","virtual"],"superClass":"Messaging.Email","interfaces":[],"blocks":[],"fields":[{"version":1,"idRange":[],"name":"BccSender","modifiers":["public"],"typeName":"System.Boolean","readAccess":"public","writeAccess":"public","dependents":[]},{"version":1,"idRange":[],"name":"Description","modifiers":["public"],"typeName":"System.String","readAccess":"public","writeAccess":"public","dependents":[]},{"version":1,"idRange":[],"name":"EmailPriority","modifiers":["public"],"typeName":"System.String","readAccess":"public","writeAccess":"public","dependents":[]},{"version":1,"idRange":[],"name":"ReplyTo","modifiers":["public"],"typeName":"System.String","readAccess":"public","writeAccess":"public","dependents":[]},{"version":1,"idRange":[],"name":"SaveAsActivity","modifiers":["public"],"typeName":"System.Boolean","readAccess":"public","writeAccess":"public","dependents":[]},{"version":1,"idRange":[],"name":"SenderDisplayName","modifiers":["public"],"typeName":"System.String","readAccess":"public","writeAccess":"public","dependents":[]},{"version":1,"idRange":[],"name":"Subject","modifiers":["public"],"typeName":"System.String","readAccess":"public","writeAccess":"public","dependents":[]},{"version":1,"idRange":[],"name":"TargetObjectIds","modifiers":["public"],"typeName":"System.List<System.Id>","readAccess":"public","writeAccess":"public","dependents":[]},{"version":1,"idRange":[],"name":"TemplateId","modifiers":["public"],"typeName":"System.Id","readAccess":"public","writeAccess":"public","dependents":[]},{"version":1,"idRange":[],"name":"UseSignature","modifiers":["public"],"typeName":"System.Boolean","readAccess":"public","writeAccess":"public","dependents":[]},{"version":1,"idRange":[],"name":"WhatIds","modifiers":["public"],"typeName":"System.List<System.Id>","readAccess":"public","writeAccess":"public","dependents":[]}],"constructors":[{"version":1,"idRange":[],"modifiers":["public"],"parameters":[],"dependents":[]}],"methods":[{"version":1,"idRange":[],"name":"getBccSender","modifiers":["public"],"typeName":"System.Boolean","parameters":[],"dependents":[]},{"version":1,"idRange":[],"name":"getDescription","modifiers":["public"],"typeName":"System.String","parameters":[],"dependents":[]},{"version":1,"idRange":[],"name":"getEmailPriority","modifiers":["public"],"typeName":"System.String","parameters":[],"dependents":[]},{"version":1,"idRange":[],"name":"getReplyTo","modifiers":["public"],"typeName":"System.String","parameters":[],"dependents":[]},{"version":1,"idRange":[],"name":"getSaveAsActivity","modifiers":["public"],"typeName":"System.Boolean","parameters":[],"dependents":[]},{"version":1,"idRange":[],"name":"getSenderDisplayName","modifiers":["public"],"typeName":"System.String","parameters":[],"dependents":[]},{"version":1,"idRange":[],"name":"getSubject","modifiers":["public"],"typeName":"System.String","parameters":[],"dependents":[]},{"version":1,"idRange":[],"name":"getTargetObjectIds","modifiers":["public"],"typeName":"System.List<System.Id>","parameters":[],"dependents":[]},{"version":1,"idRange":[],"name":"getTemplateId","modifiers":["public"],"typeName":"System.Id","parameters":[],"dependents":[]},{"version":1,"idRange":[],"name":"getUseSignature","modifiers":["public"],"typeName":"System.Boolean","parameters":[],"dependents":[]},{"version":1,"idRange":[],"name":"getWhatIds","modifiers":["public"],"typeName":"System.List<System.Id>","parameters":[],"dependents":[]},{"version":1,"idRange":[],"name":"setBccSender","modifiers":["public"],"typeName":"void","parameters":[{"version":1,"name":"param1","typeName":"System.Boolean"}],"dependents":[]},{"version":1,"idRange":[],"name":"setDescription","modifiers":["public"],"typeName":"void","parameters":[{"version":1,"name":"param1","typeName":"System.String"}],"dependents":[]},{"version":1,"idRange":[],"name":"setEmailPriority","modifiers":["public"],"typeName":"void","parameters":[{"version":1,"name":"param1","typeName":"System.String"}],"dependents":[]},{"version":1,"idRange":[],"name":"setReplyTo","modifiers":["public"],"typeName":"void","parameters":[{"version":1,"name":"param1","typeName":"System.String"}],"dependents":[]},{"version":1,"idRange":[],"name":"setSaveAsActivity","modifiers":["public"],"typeName":"void","parameters":[{"version":1,"name":"param1","typeName":"System.Boolean"}],"dependents":[]},{"version":1,"idRange":[],"name":"setSenderDisplayName","modifiers":["public"],"typeName":"void","parameters":[{"version":1,"name":"param1","typeName":"System.String"}],"dependents":[]},{"version":1,"idRange":[],"name":"setSubject","modifiers":["public"],"typeName":"void","parameters":[{"version":1,"name":"param1","typeName":"System.String"}],"dependents":[]},{"version":1,"idRange":[],"name":"setTargetObjectIds","modifiers":["public"],"typeName":"void","parameters":[{"version":1,"name":"param1","typeName":"System.List<System.Id>"}],"dependents":[]},{"version":1,"idRange":[],"name":"setTemplateId","modifiers":["public"],"typeName":"void","parameters":[{"version":1,"name":"param1","typeName":"System.Id"}],"dependents":[]},{"version":1,"idRange":[],"name":"setUseSignature","modifiers":["public"],"typeName":"void","parameters":[{"version":1,"name":"param1","typeName":"System.Boolean"}],"dependents":[]},{"version":1,"idRange":[],"name":"setWhatIds","modifiers":["public"],"typeName":"void","parameters":[{"version":1,"name":"param1","typeName":"System.List<System.Id>"}],"dependents":[]}],"nestedTypes":[],"dependents":[]}