{"sourceHash":0,"idRange":[],"name":"ProjectionNode","typeName":{"name":{"value":"ProjectionNode"},"params":[],"outer":[{"name":{"value":"Wave"},"params":[],"outer":[]}]},"nature":"class","modifiers":["public","virtual"],"superClass":[],"interfaces":[],"blocks":[],"fields":[],"constructors":[{"idRange":[],"modifiers":["public"],"parameters":[],"dependents":[]}],"methods":[{"idRange":[],"name":"alias","modifiers":["public"],"typeName":{"name":{"value":"ProjectionNode"},"params":[],"outer":[{"name":{"value":"Wave"},"params":[],"outer":[]}]},"parameters":[{"name":"name","typeName":{"name":{"value":"String"},"params":[],"outer":[{"name":{"value":"System"},"params":[],"outer":[]}]}}],"dependents":[]},{"idRange":[],"name":"avg","modifiers":["public"],"typeName":{"name":{"value":"ProjectionNode"},"params":[],"outer":[{"name":{"value":"Wave"},"params":[],"outer":[]}]},"parameters":[],"dependents":[]},{"idRange":[],"name":"build","modifiers":["public"],"typeName":{"name":{"value":"String"},"params":[],"outer":[{"name":{"value":"System"},"params":[],"outer":[]}]},"parameters":[],"dependents":[]},{"idRange":[],"name":"count","modifiers":["public"],"typeName":{"name":{"value":"ProjectionNode"},"params":[],"outer":[{"name":{"value":"Wave"},"params":[],"outer":[]}]},"parameters":[],"dependents":[]},{"idRange":[],"name":"max","modifiers":["public"],"typeName":{"name":{"value":"ProjectionNode"},"params":[],"outer":[{"name":{"value":"Wave"},"params":[],"outer":[]}]},"parameters":[],"dependents":[]},{"idRange":[],"name":"min","modifiers":["public"],"typeName":{"name":{"value":"ProjectionNode"},"params":[],"outer":[{"name":{"value":"Wave"},"params":[],"outer":[]}]},"parameters":[],"dependents":[]},{"idRange":[],"name":"sum","modifiers":["public"],"typeName":{"name":{"value":"ProjectionNode"},"params":[],"outer":[{"name":{"value":"Wave"},"params":[],"outer":[]}]},"parameters":[],"dependents":[]},{"idRange":[],"name":"unique","modifiers":["public"],"typeName":{"name":{"value":"ProjectionNode"},"params":[],"outer":[{"name":{"value":"Wave"},"params":[],"outer":[]}]},"parameters":[],"dependents":[]}],"nestedTypes":[],"dependents":[]}