{"sourceHash":0,"idRange":[],"name":"QueryBuilder","typeName":{"$type":"TypeName","name":{"value":"QueryBuilder"},"outer":[{"$type":"TypeName","name":{"value":"Wave"}}]},"nature":"class","modifiers":["public","virtual"],"superClass":[],"interfaces":[],"blocks":[],"fields":[],"constructors":[{"idRange":[],"modifiers":["public"],"parameters":[],"dependents":[]}],"methods":[{"idRange":[],"name":"cogroup","modifiers":["public","static"],"typeName":{"$type":"TypeName","name":{"value":"QueryNode"},"outer":[{"$type":"TypeName","name":{"value":"Wave"}}]},"parameters":[{"name":"cogroupNodes","typeName":{"$type":"TypeName","name":{"value":"List"},"params":[{"$type":"TypeName","name":{"value":"QueryNode"},"outer":[{"$type":"TypeName","name":{"value":"Wave"}}]}],"outer":[{"$type":"TypeName","name":{"value":"System"}}]}},{"name":"groups","typeName":{"$type":"TypeName","name":{"value":"List"},"params":[{"$type":"TypeName","name":{"value":"List"},"params":[{"$type":"TypeName","name":{"value":"String"},"outer":[{"$type":"TypeName","name":{"value":"System"}}]}],"outer":[{"$type":"TypeName","name":{"value":"System"}}]}],"outer":[{"$type":"TypeName","name":{"value":"System"}}]}}],"dependents":[]},{"idRange":[],"name":"count","modifiers":["public","static"],"typeName":{"$type":"TypeName","name":{"value":"ProjectionNode"},"outer":[{"$type":"TypeName","name":{"value":"Wave"}}]},"parameters":[],"dependents":[]},{"idRange":[],"name":"get","modifiers":["public","static"],"typeName":{"$type":"TypeName","name":{"value":"ProjectionNode"},"outer":[{"$type":"TypeName","name":{"value":"Wave"}}]},"parameters":[{"name":"projection","typeName":{"$type":"TypeName","name":{"value":"String"},"outer":[{"$type":"TypeName","name":{"value":"System"}}]}}],"dependents":[]},{"idRange":[],"name":"load","modifiers":["public","static"],"typeName":{"$type":"TypeName","name":{"value":"QueryNode"},"outer":[{"$type":"TypeName","name":{"value":"Wave"}}]},"parameters":[{"name":"datasetId","typeName":{"$type":"TypeName","name":{"value":"String"},"outer":[{"$type":"TypeName","name":{"value":"System"}}]}},{"name":"datasetVersionId","typeName":{"$type":"TypeName","name":{"value":"String"},"outer":[{"$type":"TypeName","name":{"value":"System"}}]}}],"dependents":[]},{"idRange":[],"name":"loadByDeveloperName","modifiers":["public","static"],"typeName":{"$type":"TypeName","name":{"value":"QueryNode"},"outer":[{"$type":"TypeName","name":{"value":"Wave"}}]},"parameters":[{"name":"fullyQualifiedName","typeName":{"$type":"TypeName","name":{"value":"String"},"outer":[{"$type":"TypeName","name":{"value":"System"}}]}}],"dependents":[]},{"idRange":[],"name":"union","modifiers":["public","static"],"typeName":{"$type":"TypeName","name":{"value":"QueryNode"},"outer":[{"$type":"TypeName","name":{"value":"Wave"}}]},"parameters":[{"name":"unionNodes","typeName":{"$type":"TypeName","name":{"value":"List"},"params":[{"$type":"TypeName","name":{"value":"QueryNode"},"outer":[{"$type":"TypeName","name":{"value":"Wave"}}]}],"outer":[{"$type":"TypeName","name":{"value":"System"}}]}}],"dependents":[]}],"nestedTypes":[],"dependents":[],"holders":[]}